agd_tools/anonym.py
agd_tools/anonymization.py
agd_tools/config.ini
agd_tools/config.ini.example
agd_tools/geo.py
agd_tools/pg.py
agd_tools/ssh.py
agd_tools/tools.py
agd_tools/__init__.py
agd_tools/calendar/France.py
agd_tools/calendar/periods.py
agd_tools/calendar/__init__.py
agd_tools/string_maching/standard.py
agd_tools/string_maching/__init__.py
agd_tools/string_maching/dico/__init__.py
agd_tools-0.0.6.dist-info/DESCRIPTION.rst
agd_tools-0.0.6.dist-info/METADATA
agd_tools-0.0.6.dist-info/metadata.json
agd_tools-0.0.6.dist-info/RECORD
agd_tools-0.0.6.dist-info/top_level.txt
agd_tools-0.0.6.dist-info/WHEEL
