Metadata-Version: 2.0
Name: agd-tools
Version: 0.0.6
Summary: Useful functions for datascience.
Home-page: https://github.com/SGMAP-AGD/Tools
Author: AGD Team
Author-email: UNKNOWN
License: UNKNOWN
Platform: UNKNOWN
Classifier: Development Status :: 2 - Pre-Alpha
Classifier: Programming Language :: Python :: 3
Requires-Dist: numpy
Requires-Dist: scipy
Requires-Dist: SQLAlchemy
Requires-Dist: psycopg2
Requires-Dist: pandas
Requires-Dist: paramiko
Requires-Dist: scikit-learn (>=0.17)
Requires-Dist: geographiclib
Requires-Dist: shapely
Requires-Dist: IPython
